lidar_cmn/__init__.py
lidar_cmn/config.py
lidar_cmn/download.py
lidar_cmn/generic.py
lidar_cmn/vector.py
lidar_cmn-1.1.1.dist-info/LICENSE
lidar_cmn-1.1.1.dist-info/METADATA
lidar_cmn-1.1.1.dist-info/WHEEL
lidar_cmn-1.1.1.dist-info/RECORD
